[
  {
    "id": "stage-maxime-dereymez-avril-2025",
    "type": "stage",
    "title": "Stage : Danse avec Maxime Dereymez",
    "date": "2025-04-12",
    "displayDate": "Samedi 12 avril 2025",
    "time": "16h00 - 18h00",
    "location": {
      "venue": "Salle Saussaie",
      "address": "52-54 rue de la Saussaie, 94320 THIAIS (face à la piscine)"
    },
    "description": [
      "Samba (tous niveaux) de 16h à 17h",
      "Jive (tous niveaux) de 17h à 18h"
    ],
    "pricing": [
      {
        "label": "1 cours",
        "price": "30 €"
      },
      {
        "label": "2 cours",
        "price": "50 €"
      }
    ],
    "contact": "Renseignements : 07 49 82 88 01",
    "image": "/assets/events/event-12-04-2025.jpeg",
    "isFeatured": false,
    "phoneNumber": "07 49 82 88 01"
  },
  {
    "id": "stage-son-cubano-mai-2025",
    "type": "stage",
    "title": "Stage : Son cubano Rumba guaguancó",
    "date": "2025-05-24",
    "displayDate": "Samedi 24 mai 2025",
    "time": "16h30 - 18h30",
    "location": {
      "venue": "Centre Jules Ferry",
      "address": "66 Rue Paul Vaillant Couturier, 94320 THIAIS"
    },
    "description": [
      "Stage avec Luis Jimenez"
    ],
    "pricing": [
      {
        "label": "Adhérents",
        "price": "16 €"
      },
      {
        "label": "Extérieurs",
        "price": "20 €"
      },
      {
        "label": "Enfants (accompagnés d'un adulte)",
        "price": "12 €"
      }
    ],
    "contact": "Inscription en ligne via HelloAsso / Par téléphone : 07 49 82 88 01",
    "image": "/assets/events/event-24-05-2025.jpeg",
    "isFeatured": false,
    "phoneNumber": "07 49 82 88 01"
  },
  {
    "id": "stage-beyonce-vol2-nov-2025",
    "type": "stage",
    "title": "Stage : Danse comme Beyoncé (Volume II)",
    "date": "2025-11-23",
    "displayDate": "Samedi 23 novembre 2025",
    "time": "16h30 - 18h30",
    "location": {
      "venue": "Centre de loisirs Jules Ferry",
      "address": "66 Rue Paul Vaillant Couturier, 94320 THIAIS"
    },
    "description": [
      "Animé par Marianne - Volume II"
    ],
    "pricing": [
      {
        "label": "Adhérent",
        "price": "16 €"
      },
      {
        "label": "Extérieur",
        "price": "20 €"
      }
    ],
    "contact": "Inscription : https://bit.ly/danse-comme-beyonce-volume-2",
    "image": "/assets/events/event-23-11-2025.jpeg",
    "isFeatured": false
  },
  {
    "id": "stage-son-cubano-fevrier-2026",
    "type": "stage",
    "title": "Stage : Son cubano Rumba guaguanco",
    "date": "2026-02-07",
    "displayDate": "Samedi 7 février 2026",
    "time": "16h30 - 18h30",
    "location": {
      "venue": "Centre Jules Ferry",
      "address": "66 Rue Paul Vaillant Couturier, 94320 THIAIS"
    },
    "description": [
      "Stage avec Luis Jimenez"
    ],
    "pricing": [
      {
        "label": "Adhérent",
        "price": "16 €"
      },
      {
        "label": "Extérieur",
        "price": "20 €"
      },
      {
        "label": "Enfant (accompagné d'un adulte)",
        "price": "12 €"
      }
    ],
    "contact": "Inscription en ligne via HelloAsso / Par téléphone : 07 49 82 88 01",
    "image": "/assets/events/event-07-02-2026.jpeg",
    "isFeatured": false,
    "phoneNumber": "07 49 82 88 01"
  },
  {
    "id": "stage-kpop-avril-2026",
    "type": "stage",
    "title": "K-POP Dance Workshop",
    "date": "2026-04-11",
    "displayDate": "Samedi 11 avril 2026",
    "time": "16h30",
    "location": {
      "venue": "Centre Jules Ferry de Thiais",
      "address": "66 rue Paul Vaillant Couturier, 94320 THIAIS"
    },
    "description": [
      "Stage avec Marianne",
      "Apprends une chorégraphie tendance et libère ton énergie !",
      "Tous niveaux, ambiance fun & dynamique. Good vibes garanties."
    ],
    "pricing": [
      {
        "label": "Tarif Adhérent",
        "price": "16 €"
      },
      {
        "label": "Tarif Extérieur",
        "price": "20 €"
      }
    ],
    "contact": "Contact : 07 49 82 88 01",
    "extraInfo": "Places limitées !",
    "image": "/assets/events/event-11-04-2026.jpeg",
    "isFeatured": false,
    "phoneNumber": "07 49 82 88 01"
  },
  {
    "id": "soiree-vacances-2026",
    "type": "soiree",
    "title": "Soiree Vacances JAMM Dance",
    "date": "2026-06-06",
    "displayDate": "Samedi 6 juin 2026",
    "time": "19h30 (Demo des eleves a 20h00)",
    "location": {
      "venue": "Salle",
      "address": "111 rue du Pave de Grignon, 94320 THIAIS"
    },
    "description": [
      "Salsa, Bachata, Rock, Madison, Annees 80...",
      "Soiree toutes danses !!!"
    ],
    "pricing": [
      {
        "label": "Adherents",
        "price": "6 EUR"
      },
      {
        "label": "Autres",
        "price": "8 EUR"
      }
    ],
    "contact": "Inscription par telephone : 07 49 82 88 01",
    "extraInfo": "Un petit plat salé ou sucré sera le bienvenu !",
    "image": "/assets/events/soiree-vacance.jpeg",
    "isFeatured": false,
    "phoneNumber": "07 49 82 88 01"
  },
  {
    "id": "stage-yann-juin-2026",
    "type": "stage",
    "title": "2 Stages de Danse avec Yann",
    "date": "2026-06-28",
    "displayDate": "Dimanche 28 juin 2026",
    "time": "16h00 (PASO DOBLE) et 17h00 (CHARLESTON)",
    "location": {
      "venue": "Salle Saussaie (face a la piscine)",
      "address": "52-54 rue de la Saussaie, 94320 THIAIS"
    },
    "description": [
      "PASO DOBLE - Tous niveaux (sur la musique de 'Pirate des Caraibes')",
      "CHARLESTON - Tous niveaux (sur la musique 'Etre un homme comme vous' de Ben l'Oncle Soul)"
    ],
    "pricing": [
      {
        "label": "1 cours",
        "price": "30 EUR"
      },
      {
        "label": "2 cours",
        "price": "50 EUR"
      }
    ],
    "promotion": "Reduction 10 % pour toute inscription avant le 17 mai 26 avec le code JAMMYA10",
    "contact": "Renseignements : 07 49 82 88 01",
    "extraInfo": "Cheques ANCV acceptes",
    "image": "/assets/events/stage-yann.png",
    "isFeatured": false,
    "paymentUrl": "https://www.helloasso.com/associations/jamm-dance/evenements/danse-avec-yann-alrick-mortreuil",
    "phoneNumber": "07 49 82 88 01"
  },
  {
    "id": "forum-activites-thiaisiennes-2026",
    "type": "autre",
    "title": "Forum des Activités Thiaisiennes",
    "date": "2026-09-05",
    "displayDate": "Samedi 05 septembre 2026",
    "time": "10h00 - 17h00",
    "location": {
      "venue": "Palais Omnisports de Thiais",
      "address": "Thiais"
    },
    "description": [
      "Venez retrouver l'association JAMM Dance au Forum des Activités Thiaisiennes !"
    ],
    "pricing": [
      {
        "label": "Entrée",
        "price": "Libre (Gratuit)"
      }
    ],
    "contact": "Pour plus d'infos : 01 48 92 42 60 - www.ville-thiais.fr",
    "image": "/assets/events/2026-Forum-des-activites-thiaisiennes-2026-694x1024.jpg",
    "phoneNumber": "01 48 92 42 60",
    "isFeatured": true
  },
  {
    "id": "forum-associations-mandres-les-roses-2026",
    "type": "autre",
    "title": "Forum des Associations - Mandres-les-Roses",
    "date": "2026-09-13",
    "displayDate": "Dimanche 13 septembre 2026",
    "time": "10h00 - 18h00",
    "location": {
      "venue": "Parc Beauséjour",
      "address": "Mandres-les-Roses"
    },
    "description": [
      "Trouvez votre passion, rejoignez l'aventure !",
      "Venez rencontrer l'équipe de JAMM Dance au Forum des Associations de Mandres-les-Roses. L'occasion parfaite pour échanger avec nous et préparer la rentrée de danse."
    ],
    "pricing": [
      {
        "label": "Entrée",
        "price": "Libre (Gratuit)"
      }
    ],
    "contact": "Réseaux sociaux de la ville : @villedemandreslesroses",
    "image": "/assets/events/forum-mandres-les-roses-2026.jpeg",
    "isFeatured": true
  }
]